scisoftpy/__init__.py
scisoftpy/crystallography.py
scisoftpy/data.py
scisoftpy/dictutils.py
scisoftpy/diffraction.py
scisoftpy/external.py
scisoftpy/fft.py
scisoftpy/flatten.py
scisoftpy/image.py
scisoftpy/io.py
scisoftpy/linalg.py
scisoftpy/plot.py
scisoftpy/random.py
scisoftpy/roi.py
scisoftpy/rpc.py
scisoftpy/signal.py
scisoftpy/fit/__init__.py
scisoftpy/jython/__init__.py
scisoftpy/jython/fitcore.py
scisoftpy/jython/function.py
scisoftpy/jython/jybeans.py
scisoftpy/jython/jycomparisons.py
scisoftpy/jython/jycore.py
scisoftpy/jython/jycrystallography.py
scisoftpy/jython/jydata.py
scisoftpy/jython/jydiffraction.py
scisoftpy/jython/jyfft.py
scisoftpy/jython/jyflatten.py
scisoftpy/jython/jyhdf5io.py
scisoftpy/jython/jyimage.py
scisoftpy/jython/jyio.py
scisoftpy/jython/jylinalg.py
scisoftpy/jython/jymaths.py
scisoftpy/jython/jynxio.py
scisoftpy/jython/jyplot.py
scisoftpy/jython/jyplottingsystem.py
scisoftpy/jython/jyrandom.py
scisoftpy/jython/jyroi.py
scisoftpy/jython/jyrpc.py
scisoftpy/jython/jyscisoft.py
scisoftpy/jython/jysignal.py
scisoftpy/jython/jywrapper.py
scisoftpy/nexus/__init__.py
scisoftpy/nexus/hdf5.py
scisoftpy/nexus/nxclasses.py
scisoftpy/nexus/utils.py
scisoftpy/python/__init__.py
scisoftpy/python/pybeans.py
scisoftpy/python/pycomparisons.py
scisoftpy/python/pycore.py
scisoftpy/python/pydata.py
scisoftpy/python/pyflatten.py
scisoftpy/python/pyh5py.py
scisoftpy/python/pyhdf5io.py
scisoftpy/python/pyio.py
scisoftpy/python/pymaths.py
scisoftpy/python/pynxio.py
scisoftpy/python/pyplot.py
scisoftpy/python/pyplottingsystem.py
scisoftpy/python/pyroi.py
scisoftpy/python/pyrpc.py
scisoftpy/python/pyscisoft.py
scisoftpy/python/pysignal.py
scisoftpy/python/pywrapper.py
scisoftpy-2.37.1.dist-info/METADATA
scisoftpy-2.37.1.dist-info/WHEEL
scisoftpy-2.37.1.dist-info/top_level.txt
scisoftpy-2.37.1.dist-info/RECORD
